[
    {
      "X": 574282,
      "Y": 4781249.55,
      "OBJECTID": 51,
      "TYPE": "Motel",
      "NAME": "Pleasant Stay",
      "LOCATION": "2692 Wilson Street West, Ancaster, ON",
      "PHONE": "905-648-2728",
      "FAX": "",
      "URL": "http://www.booking.com/hotel/ca/pleasant-stay-motel.en.html?aid=311088;label=pleasant-stay-motel-uCL57VDo2lE3owmO1lT*ZAS12873663723:pl:ta:p1:p2:ac:ap1t1:neg;ws=&gclid=CJnR5LHYq7QCFcU-MgodfjcAow",
      "LONGITUDE": -80.08598232953338,
      "LATITUDE": 43.18036274324761
    },
    {
      "X": 602686.9299999997,
      "Y": 4786124.68,
      "OBJECTID": 52,
      "TYPE": "Motel",
      "NAME": "Stoney Creek",
      "LOCATION": "254 Highway No. 8, Stoney Creek, ON",
      "PHONE": "905-662-8844",
      "FAX": "",
      "URL": "http://www.stoneycreekmotel.ca/",
      "LONGITUDE": -79.73563394231437,
      "LATITUDE": 43.22092585180876
    },
    {
      "X": 605589.9336000001,
      "Y": 4785269.220899999,
      "OBJECTID": 53,
      "TYPE": "Motel",
      "NAME": "Fruitland",
      "LOCATION": "687 Highway No. 8, Stoney Creek, ON",
      "PHONE": "905-643-2931",
      "FAX": "",
      "URL": "http://lodging.worldweb.com/4-184801-Fruitland_Motel.html",
      "LONGITUDE": -79.70006229841833,
      "LATITUDE": 43.21282405634096
    },
    {
      "X": 589162.7547000004,
      "Y": 4797785.9517,
      "OBJECTID": 54,
      "TYPE": "Motel",
      "NAME": "Waterdown",
      "LOCATION": "219 Highway No. 5 East, Waterdown, ON",
      "PHONE": "905-689-5278",
      "FAX": "",
      "URL": "http://www.staycanada.ca/17877-waterdown_motel_waterdown/",
      "LONGITUDE": -79.90023327588412,
      "LATITUDE": 43.32763135235884
    },
    {
      "X": 604393.7999999998,
      "Y": 4787907.55,
      "OBJECTID": 55,
      "TYPE": "Motel",
      "NAME": "Lake Trail",
      "LOCATION": "423 North Service Road, Stoney Creek, ON",
      "PHONE": "905-662-1599",
      "FAX": "",
      "URL": "http://www.yellowpages.ca/bus/Ontario/Stoney-Creek/Lake-Trail-Motel/4393132.html",
      "LONGITUDE": -79.71428533268711,
      "LATITUDE": 43.23674188447921
    },
    {
      "X": 587292.5499999998,
      "Y": 4795410.04,
      "OBJECTID": 56,
      "TYPE": "Motel",
      "NAME": "Escarpment Motor Inn",
      "LOCATION": "76 Highway No. 5 West, Waterdown, ON",
      "PHONE": "905-689-6969",
      "FAX": "",
      "URL": "http://www.yellowpages.ca/bus/Ontario/Waterdown/Escarpment-Motor-Inn/6666871.html",
      "LONGITUDE": -79.92367469057345,
      "LATITUDE": 43.30646048739343
    },
    {
      "X": 591321.6438999996,
      "Y": 4789984.0313,
      "OBJECTID": 57,
      "TYPE": "Hotel",
      "NAME": "Homewood Suites by Hilton",
      "LOCATION": "40 Bay Street South,  Hamilton,  Ontario",
      "PHONE": "905-667-1200",
      "FAX": "905-667-1201",
      "URL": "http://homewoodsuites3.hilton.com/en/hotels/ontario/homewood-suites-by-hilton-hamilton-ontario-canada-YHMHWHW/index.html",
      "LONGITUDE": -79.87490541982142,
      "LATITUDE": 43.25713242040322
    },
    {
      "X": 595659.0344000002,
      "Y": 4783066.9361,
      "OBJECTID": 1,
      "TYPE": "Hotel",
      "NAME": "Best Western Premier C Hotel by Carmen's",
      "LOCATION": "1530 Stone Church Road East, Hamilton, ON",
      "PHONE": "905-381-9898",
      "FAX": "905-381-9888",
      "URL": "http://bestwesternontario.com/hotels/best-western-premier-c-hotel-by-carmens",
      "LONGITUDE": -79.82267822994501,
      "LATITUDE": 43.19432099559931
    },
    {
      "X": 591210.9912,
      "Y": 4790079.6115,
      "OBJECTID": 2,
      "TYPE": "Hotel",
      "NAME": "Staybridge Suites Hamilton - Downtown",
      "LOCATION": "20 Caroline Street South, Hamilton, ON",
      "PHONE": "905-527-1001",
      "FAX": "",
      "URL": "http://www.staybridge.com/hotels/us/en/hamilton/yhmha/hoteldetail?dp=true",
      "LONGITUDE": -79.87625259268576,
      "LATITUDE": 43.25800632293813
    },
    {
      "X": 590245.1511000004,
      "Y": 4785344.5954,
      "OBJECTID": 3,
      "TYPE": "Hotel",
      "NAME": "Courtyard Hamilton Marriott",
      "LOCATION": "1224 Upper James Street, Hamilton, ON",
      "PHONE": "905-383-7772",
      "FAX": "905-383-7895",
      "URL": "http://www.marriott.com/hotels/travel/yhmcy-courtyard-hamilton/",
      "LONGITUDE": -79.88892471893976,
      "LATITUDE": 43.215493150236824
    },
    {
      "X": 592420.2340000002,
      "Y": 4789533.7179,
      "OBJECTID": 4,
      "TYPE": "Hotel",
      "NAME": "Days Inn Hamilton",
      "LOCATION": "210 Main Street East, Hamilton, ON",
      "PHONE": "905-528-3297",
      "FAX": "905-528-0101",
      "URL": "http://www.hamiltondaysinn.com/",
      "LONGITUDE": -79.86144879290677,
      "LATITUDE": 43.25294438178137
    },
    {
      "X": 590409.5990000004,
      "Y": 4791128.3705,
      "OBJECTID": 5,
      "TYPE": "Hotel",
      "NAME": "Admiral Inn Hamilton",
      "LOCATION": "149 Dundurn Street North, Hamilton, ON",
      "PHONE": "905-529-2311",
      "FAX": "905-529-9100",
      "URL": "http://www.admiralinnhamilton.com/",
      "LONGITUDE": -79.88595198010026,
      "LATITUDE": 43.267544827680176
    },
    {
      "X": 600515.6955000004,
      "Y": 4787650.757999999,
      "OBJECTID": 6,
      "TYPE": "Hotel",
      "NAME": "Comfort Inn",
      "LOCATION": "183 Centennial Parkway North, Hamilton, ON",
      "PHONE": "905-560-4500",
      "FAX": "905-560-6223",
      "URL": "http://www.choicehotels.ca/hotels/hotel?hotel=CN268",
      "LONGITUDE": -79.76208375023293,
      "LATITUDE": 43.234956876083835
    },
    {
      "X": 590441.0360000003,
      "Y": 4785415.6524,
      "OBJECTID": 7,
      "TYPE": "Hotel",
      "NAME": "Howard Johnson Hamilton",
      "LOCATION": "1187 Upper James Street, Hamilton, ON",
      "PHONE": "905-575-9666",
      "FAX": "905-575-1098",
      "URL": "http://www.hojo.com/HowardJohnson/control/Booking/property_info?propertyId=32482",
      "LONGITUDE": -79.8865018382316,
      "LATITUDE": 43.216109433534356
    },
    {
      "X": 600727.9036999997,
      "Y": 4788694.260299999,
      "OBJECTID": 8,
      "TYPE": "Hotel",
      "NAME": "Holiday Inn Express Hamilton/Stoney Creek",
      "LOCATION": "51 Keefer Court, Stoney Creek, ON",
      "PHONE": "905-578-1212",
      "FAX": "905-578-6468",
      "URL": "http://www.ichotelsgroup.com/h/d/ex/1/en/hd/yhmex?irs=null",
      "LONGITUDE": -79.75928023769515,
      "LATITUDE": 43.24432279894282
    },
    {
      "X": 590170.2202000003,
      "Y": 4788078.855799999,
      "OBJECTID": 9,
      "TYPE": "Campus",
      "NAME": "Mohawk Residence & Conference Centre - Hamilton",
      "LOCATION": "245 Fennell Avenue West, Hamilton, ON",
      "PHONE": "905-385-3200",
      "FAX": "905-385-2170",
      "URL": "http://www.stayrcc.com/hamilton/",
      "LONGITUDE": -79.88940019293176,
      "LATITUDE": 43.240118752130364
    },
    {
      "X": 592167.3625999996,
      "Y": 4789742.3938,
      "OBJECTID": 10,
      "TYPE": "Hotel",
      "NAME": "Crowne Plaza Hotel",
      "LOCATION": "150 King Street East, Hamilton, ON",
      "PHONE": "905-528-3451",
      "FAX": "905-522-2281",
      "URL": "http://www.ihg.com/crowneplaza/hotels/us/en/hamilton/yhmcp/hoteldetail",
      "LONGITUDE": -79.86452847980533,
      "LATITUDE": 43.25485403446715
    },
    {
      "X": 591551.0525000002,
      "Y": 4790079.658299999,
      "OBJECTID": 11,
      "TYPE": "Hotel",
      "NAME": "Sheraton Hamilton Hotel",
      "LOCATION": "116 King Street West, Hamilton, ON",
      "PHONE": "905-529-5515",
      "FAX": "905-529-8266",
      "URL": "http://www.starwoodhotels.com/sheraton/property/overview/index.html?propertyID=185",
      "LONGITUDE": -79.87206371979389,
      "LATITUDE": 43.25796551371969
    },
    {
      "X": 589553.5127999997,
      "Y": 4790277.4035,
      "OBJECTID": 12,
      "TYPE": "Hotel",
      "NAME": "Visitors Inn Hotel",
      "LOCATION": "649 Main Street West, Hamilton, ON",
      "PHONE": "905-529-6979",
      "FAX": "905-529-6979",
      "URL": "http://www.visitorsinn.com/",
      "LONGITUDE": -79.89663732921255,
      "LATITUDE": 43.25998581259859
    },
    {
      "X": 587421.5565,
      "Y": 4790558.050899999,
      "OBJECTID": 13,
      "TYPE": "Campus",
      "NAME": "McMaster Housing and Conference Services",
      "LOCATION": "1280 Main Street West, Hamilton, ON",
      "PHONE": "905-525-9140 X 24781",
      "FAX": "905-524-2611",
      "URL": "http://housing.mcmaster.ca/index.php",
      "LONGITUDE": -79.92285538341444,
      "LATITUDE": 43.26276282990714
    },
    {
      "X": 591149.3279999997,
      "Y": 4789953.5704,
      "OBJECTID": 14,
      "TYPE": "Hotel",
      "NAME": "Arrival Inn",
      "LOCATION": "175 Main Street West, Hamilton, ON",
      "PHONE": "905-528-0611",
      "FAX": "905-528-1130",
      "URL": "http://www.arrivalinn.com/",
      "LONGITUDE": -79.87703301387721,
      "LATITUDE": 43.256879040900586
    },
    {
      "X": 588556.6184999999,
      "Y": 4779369.988399999,
      "OBJECTID": 15,
      "TYPE": "Hotel",
      "NAME": "Super 8 Mount Hope",
      "LOCATION": "2975 Homestead Drive, Mount Hope, ON",
      "PHONE": "905-679-3355",
      "FAX": "905-679-5109",
      "URL": "http://www.super8.com/hotels/ontario/mount-hope/super8-mt-hope-hamilton-intl-arpt-on/hotel-overview?partner_id=&hotel_id=08259",
      "LONGITUDE": -79.91066687452074,
      "LATITUDE": 43.16190280154129
    },
    {
      "X": 580639.0416000001,
      "Y": 4784991.445,
      "OBJECTID": 16,
      "TYPE": "Bed and Breakfast",
      "NAME": "Carole's Bed and Breakfast",
      "LOCATION": "167 Daniels Street, Ancaster, ON",
      "PHONE": "905-304-6629",
      "FAX": "",
      "URL": "http://www.bbcanada.com/5409.html",
      "LONGITUDE": -80.007225826897,
      "LATITUDE": 43.213401024580605
    },
    {
      "X": 578767.8583000004,
      "Y": 4803269.7902,
      "OBJECTID": 17,
      "TYPE": "Bed and Breakfast",
      "NAME": "Cedarbrook Farm",
      "LOCATION": "812 8th Concession Road West, Puslinch, ON",
      "PHONE": "905-659-1566",
      "FAX": "905-659-0681",
      "URL": "http://www.bedbreakfasthome.com/cedarbrookfarm/",
      "LONGITUDE": -80.02764050420244,
      "LATITUDE": 43.37816453235751
    },
    {
      "X": 577525.9434000002,
      "Y": 4778542.6629,
      "OBJECTID": 18,
      "TYPE": "Bed and Breakfast",
      "NAME": "Duck Tail Inn",
      "LOCATION": "1573 Butter Road West, Ancaster, ON",
      "PHONE": "905-648-3596",
      "FAX": "",
      "URL": "",
      "LONGITUDE": -80.04645110434305,
      "LATITUDE": 43.15566525652564
    },
    {
      "X": 585413.9585999995,
      "Y": 4790418.2202,
      "OBJECTID": 19,
      "TYPE": "Bed and Breakfast",
      "NAME": "Glenwood Bed and Breakfast",
      "LOCATION": "42 Osler Drive, Dundas, ON",
      "PHONE": "905-628-8104",
      "FAX": "",
      "URL": "http://www.glenwoodbb.ca/",
      "LONGITUDE": -79.94760908503588,
      "LATITUDE": 43.26173414495901
    },
    {
      "X": 593952.1409999998,
      "Y": 4788672.8495,
      "OBJECTID": 20,
      "TYPE": "Bed and Breakfast",
      "NAME": "Heritage House 1914",
      "LOCATION": "202 St. Clair Boulevard, Hamilton, ON",
      "PHONE": "905-549-5247",
      "FAX": "",
      "URL": "http://www.bedbreakfasthome.com/heritagehouse1914bedandbreakfast/",
      "LONGITUDE": -79.84272729889862,
      "LATITUDE": 43.24500473458689
    },
    {
      "X": 588131.4287999999,
      "Y": 4778484.7908,
      "OBJECTID": 21,
      "TYPE": "Bed and Breakfast",
      "NAME": "Homestead House",
      "LOCATION": "3272 Homestead Drive, Mount Hope, ON",
      "PHONE": "905-679-2581",
      "FAX": "905-639-4860",
      "URL": "http://www.bbcanada.com/homesteadhouse",
      "LONGITUDE": -79.91603710587792,
      "LATITUDE": 43.15398284061876
    },
    {
      "X": 591248.2631999999,
      "Y": 4789130.6794,
      "OBJECTID": 22,
      "TYPE": "Bed and Breakfast",
      "NAME": "Ivy Manor",
      "LOCATION": "272 Park Street South, Hamilton, ON",
      "PHONE": "905-521-0925",
      "FAX": "905-521-1555",
      "URL": "http://www.bedbreakfasthome.com/ivymanor1710/?from=listing",
      "LONGITUDE": -79.87595063227579,
      "LATITUDE": 43.24945861936196
    },
    {
      "X": 588417.2663000003,
      "Y": 4775811.0709,
      "OBJECTID": 23,
      "TYPE": "Bed and Breakfast",
      "NAME": "Log Inn",
      "LOCATION": "8211 Chippewa Road East, Mount Hope, ON",
      "PHONE": "905-679-1876",
      "FAX": "905-679-0431",
      "URL": "http://www.loginnbb.ca/loginne.htm",
      "LONGITUDE": -79.9129487131922,
      "LATITUDE": 43.129877335169425
    },
    {
      "X": 593537.5102000004,
      "Y": 4788276.7741,
      "OBJECTID": 24,
      "TYPE": "Bed and Breakfast",
      "NAME": "Rose Arden",
      "LOCATION": "266 Mountain Park Avenue, Hamilton, ON",
      "PHONE": "905-387-2000",
      "FAX": "",
      "URL": "http://www.rosearden.com/",
      "LONGITUDE": -79.84790078012925,
      "LATITUDE": 43.24149046365089
    },
    {
      "X": 591269.6616000002,
      "Y": 4789058.568399999,
      "OBJECTID": 25,
      "TYPE": "Bed and Breakfast",
      "NAME": "Rutherford House",
      "LOCATION": "293 Park Street South, Hamilton, ON",
      "PHONE": "905-525-2422",
      "FAX": "905-525-5236",
      "URL": "http://www.rutherfordbb.com/",
      "LONGITUDE": -79.87569902733831,
      "LATITUDE": 43.24880681728534
    },
    {
      "X": 594169.9222999997,
      "Y": 4785767.7554,
      "OBJECTID": 26,
      "TYPE": "Bed and Breakfast",
      "NAME": "Sadwick's Place",
      "LOCATION": "725 Mohawk Road East, Hamilton, ON",
      "PHONE": "905-383-2783",
      "FAX": "",
      "URL": "http://www.bbcanada.com/1137.html",
      "LONGITUDE": -79.84054124644595,
      "LATITUDE": 43.218823364597725
    },
    {
      "X": 581106.8110999996,
      "Y": 4784568.0188,
      "OBJECTID": 27,
      "TYPE": "Bed and Breakfast",
      "NAME": "Tranquility Base",
      "LOCATION": "110 Abbey Close, Ancaster, ON",
      "PHONE": "905-648-1506",
      "FAX": "905-648-9104",
      "URL": "http://www.tranquilitybase.on.ca",
      "LONGITUDE": -80.0015300117176,
      "LATITUDE": 43.2095386391478
    },
    {
      "X": 591966.6086999997,
      "Y": 4790861.7989,
      "OBJECTID": 28,
      "TYPE": "Bed and Breakfast",
      "NAME": "MacNab Terrace Guest House",
      "LOCATION": "256-258 MacNab Street North, Hamilton, ON",
      "PHONE": "905-572-7878",
      "FAX": "905-572-9625",
      "URL": "http://www.macnabterrace.ca",
      "LONGITUDE": -79.86681431945398,
      "LATITUDE": 43.26495646480672
    },
    {
      "X": 591985.3669999996,
      "Y": 4790613.1227,
      "OBJECTID": 29,
      "TYPE": "Bed and Breakfast",
      "NAME": "An Architect's Guest House",
      "LOCATION": "237 1/2 James Street North, Hamilton, ON",
      "PHONE": "905-870-9671",
      "FAX": "",
      "URL": "http://tourismhamilton.com/events/viewPartner.php?partnerID=130868&refer=stay",
      "LONGITUDE": -79.86662476794604,
      "LATITUDE": 43.26271536634761
    },
    {
      "X": 582646.1003,
      "Y": 4783598.51,
      "OBJECTID": 30,
      "TYPE": "Bed and Breakfast",
      "NAME": "The Fiddler's Inn",
      "LOCATION": "558 Fiddler's Green Road, Ancaster, ON",
      "PHONE": "905-648-0045",
      "FAX": "905-648-0330",
      "URL": "http://www.bedbreakfasthome.com/thefiddlersinn/",
      "LONGITUDE": -79.98272847282331,
      "LATITUDE": 43.20064287591159
    },
    {
      "X": 589937.3503999999,
      "Y": 4785328.7389,
      "OBJECTID": 31,
      "TYPE": "Bed and Breakfast",
      "NAME": "Cottage in the City",
      "LOCATION": "918 West 5th Street, Hamilton, ON",
      "PHONE": "905-389-5067",
      "FAX": "",
      "URL": "http://www.bbcanada.com/8212.html",
      "LONGITUDE": -79.89271617052881,
      "LATITUDE": 43.21538713125256
    },
    {
      "X": 591922.1014999999,
      "Y": 4791396.1175999995,
      "OBJECTID": 32,
      "TYPE": "Bed and Breakfast",
      "NAME": "Mulberry House Suites",
      "LOCATION": "78 Ferrie Street West, Hamilton, ON",
      "PHONE": "905-518-1493",
      "FAX": "",
      "URL": "http://www.mulberryhouse.ca/",
      "LONGITUDE": -79.86727341289122,
      "LATITUDE": 43.26977231612563
    },
    {
      "X": 585346.8098,
      "Y": 4790322.3767,
      "OBJECTID": 33,
      "TYPE": "Bed and Breakfast",
      "NAME": "Osler House",
      "LOCATION": "30 South Street West, Dundas, ON",
      "PHONE": "289-238-9278",
      "FAX": "",
      "URL": "http://www.oslerhouse.com/",
      "LONGITUDE": -79.94845114518576,
      "LATITUDE": 43.2608788588267
    },
    {
      "X": 580363.9215000002,
      "Y": 4781537.259099999,
      "OBJECTID": 34,
      "TYPE": "Bed and Breakfast",
      "NAME": "Ridgemoor",
      "LOCATION": "902 Shaver Road, Ancaster, ON",
      "PHONE": "905-648-0116",
      "FAX": "",
      "URL": "http://www.ridgemoor.ca/",
      "LONGITUDE": -80.01111481500024,
      "LATITUDE": 43.18233083164917
    },
    {
      "X": 576032.2603000002,
      "Y": 4782153.6121,
      "OBJECTID": 35,
      "TYPE": "Bed and Breakfast",
      "NAME": "Serenity Ranch",
      "LOCATION": "2171 Wilson Street West, Jerseyville, ON",
      "PHONE": "289-346-0278",
      "FAX": "",
      "URL": "http://www.serenityranchbb.com/",
      "LONGITUDE": -80.06432436759616,
      "LATITUDE": 43.18832848523065
    },
    {
      "X": 580804.0099999998,
      "Y": 4784507.85,
      "OBJECTID": 36,
      "TYPE": "Bed and Breakfast",
      "NAME": "The Meadows",
      "LOCATION": "58 Galley Road, Ancaster, ON",
      "PHONE": "905-648-6853",
      "FAX": "",
      "URL": "http://www.bbcanada.com/10178.html",
      "LONGITUDE": -80.00526591445613,
      "LATITUDE": 43.209029385459964
    },
    {
      "X": 581253.8033999996,
      "Y": 4778180.788,
      "OBJECTID": 37,
      "TYPE": "Bed and Breakfast",
      "NAME": "The Shaver's",
      "LOCATION": "1868 Shaver Road, Ancaster, ON",
      "PHONE": "905-648-3326",
      "FAX": "",
      "URL": "http://www.theshaversbnb.ca/",
      "LONGITUDE": -80.00065917019754,
      "LATITUDE": 43.152015836842594
    },
    {
      "X": 566561.9500000002,
      "Y": 4791596.5671,
      "OBJECTID": 38,
      "TYPE": "Bed and Breakfast",
      "NAME": "Weekswood Farm",
      "LOCATION": "585 Hunter Road, Troy, ON",
      "PHONE": "519-647-3343",
      "FAX": "519-647-3343",
      "URL": "http://www.bnbstar.ca/id_351686.html",
      "LONGITUDE": -80.17971678248097,
      "LATITUDE": 43.27424472116765
    },
    {
      "X": 585376.3415,
      "Y": 4784511.6675,
      "OBJECTID": 39,
      "TYPE": "Campus",
      "NAME": "Redeemer Conference Accomodations",
      "LOCATION": "777 Garner Road East, Ancaster, ON",
      "PHONE": "905-648-2131 ext4124",
      "FAX": "",
      "URL": "http://www.redeemer.ca/about/campusServices/conferenceServices/ConferenceAccommodations.aspx",
      "LONGITUDE": -79.94898688151578,
      "LATITUDE": 43.20856053281248
    },
    {
      "X": 585980.3729999997,
      "Y": 4789254.5963,
      "OBJECTID": 40,
      "TYPE": "Motel",
      "NAME": "Hamilton Inn",
      "LOCATION": "1870 Main Street West, Hamilton, ON",
      "PHONE": "905-528-8383",
      "FAX": "",
      "URL": "http://www.hamiltoninn.ca/index.html",
      "LONGITUDE": -79.9408130343988,
      "LATITUDE": 43.25119345936599
    },
    {
      "X": 593686.17,
      "Y": 4789446.7,
      "OBJECTID": 41,
      "TYPE": "Hotel",
      "NAME": "Budget Inn Hamilton",
      "LOCATION": "737 King Street East, Hamilton, ON",
      "PHONE": "905-527-2708",
      "FAX": "",
      "URL": "http://www.budgetinnhamilton.com/",
      "LONGITUDE": -79.845871245062,
      "LATITUDE": 43.25200470188423
    },
    {
      "X": 598964.79,
      "Y": 4791932.14,
      "OBJECTID": 42,
      "TYPE": "Motel",
      "NAME": "Beach Motor Inn",
      "LOCATION": "400 Beach Boulevard, Hamilton, ON",
      "PHONE": "905-547-8906",
      "FAX": "",
      "URL": "http://www.yellowpages.ca/bus/Ontario/Hamilton/Beach-Motor-Inn-Motel/167831.html?what=motels+and+inns&where=Hamilton%2C+ON&le=cd13c6d21a%7C1379edcb21a",
      "LONGITUDE": -79.78041085598134,
      "LATITUDE": 43.273705719447
    },
    {
      "X": 599259.3499999996,
      "Y": 4787236.06,
      "OBJECTID": 43,
      "TYPE": "Motel",
      "NAME": "Red Rose",
      "LOCATION": "553 Queenston Road, Hamilton, ON",
      "PHONE": "905-560-7060",
      "FAX": "",
      "URL": "http://www.yellowpages.ca/bus/Ontario/Hamilton/Red-Rose-Motel/5982867.html?what=motels+and+inns&where=Hamilton%2C+ON&le=9ed6979b5a",
      "LONGITUDE": -79.77762761755159,
      "LATITUDE": 43.23138985857902
    },
    {
      "X": 600764.7000000002,
      "Y": 4788438.75,
      "OBJECTID": 44,
      "TYPE": "Motel",
      "NAME": "Pines",
      "LOCATION": "395 Centennial Parkway North, Hamilton, ON",
      "PHONE": "905-561-5652",
      "FAX": "",
      "URL": "http://www.yellowpages.ca/bus/Ontario/Hamilton/Pines-Motel/2669659.html",
      "LONGITUDE": -79.75887380506843,
      "LATITUDE": 43.242017628143486
    },
    {
      "X": 610999.2345000003,
      "Y": 4784500.0231,
      "OBJECTID": 45,
      "TYPE": "Bed and Breakfast",
      "NAME": "Caboose One",
      "LOCATION": "1468 Highway No. 8, Winona, ON",
      "PHONE": "905-643-1015",
      "FAX": "",
      "URL": "http://tourismhamilton.com/events/viewPartner.php?partnerID=109736&refer=stay",
      "LONGITUDE": -79.6336400862954,
      "LATITUDE": 43.20512359254752
    },
    {
      "X": 592377.7089,
      "Y": 4790273.513599999,
      "OBJECTID": 46,
      "TYPE": "Other",
      "NAME": "Hamilton Guesthouse",
      "LOCATION": "158 Mary Street, Hamilton, ON",
      "PHONE": "289-396-1659",
      "FAX": "",
      "URL": "http://www.hamiltonguesthouse.info/",
      "LONGITUDE": -79.86184851821481,
      "LATITUDE": 43.259609905951976
    },
    {
      "X": 574079.0542000001,
      "Y": 4787966.1021,
      "OBJECTID": 47,
      "TYPE": "Bed and Breakfast",
      "NAME": "Maple Acres Retreat",
      "LOCATION": "35 Orkney Road, Lynden, ON",
      "PHONE": "905-617-6700",
      "FAX": "905-921-3481",
      "URL": "http://lodging.worldweb.com/4-211305-Maple_Acres_Retreat_Lynden.html",
      "LONGITUDE": -80.08757812734024,
      "LATITUDE": 43.24085591483612
    },
    {
      "X": 584758.3378999997,
      "Y": 4791119.3411,
      "OBJECTID": 48,
      "TYPE": "Bed and Breakfast",
      "NAME": "The Homestead 1867",
      "LOCATION": "36 Melville Street, Dundas, ON",
      "PHONE": "289-238-8720",
      "FAX": "",
      "URL": "http://www.thehomestead1867.ca/",
      "LONGITUDE": -79.9555777891615,
      "LATITUDE": 43.268120484452545
    },
    {
      "X": 579877.2640000004,
      "Y": 4783495.1804,
      "OBJECTID": 49,
      "TYPE": "Motel",
      "NAME": "Motel California",
      "LOCATION": "1075 Wilson Street West, Ancaster, ON",
      "PHONE": "905-648-1821",
      "FAX": "",
      "URL": "http://www.yellowpages.ca/bus/Ontario/Ancaster/Motel-California/1089087.html",
      "LONGITUDE": -80.01681936725629,
      "LATITUDE": 43.200010499122705
    },
    {
      "X": 579498.8200000003,
      "Y": 4783183.44,
      "OBJECTID": 50,
      "TYPE": "Motel",
      "NAME": "Maple Farm",
      "LOCATION": "1185 Wilson Street West, Ancaster, ON",
      "PHONE": "905-648-4466",
      "FAX": "",
      "URL": "http://www.profilecanada.com/companydetail.cfm?company=2344745_Maple_Farms_Motel_Ancaster_ON",
      "LONGITUDE": -80.02152168529922,
      "LATITUDE": 43.19724368983545
    }
  ]